<floor id="101001310006" location="ShuangAnShangChang" floor="F5" north="0.0">
	<feature id="1010013100060000" shape="0" type="1" name="Nike" url="">
		<nd x="15.025879" y="94.919312" />
		<nd x="15.025879" y="79.477112" />
		<nd x="8.110474" y="79.477112" />
		<nd x="8.110474" y="84.378479" />
		<nd x="2.000671" y="84.378479" />
		<nd x="2.000671" y="94.919312" />
		<center x="9.11822509766" y="88.1201782227" />
	</feature>
	<feature id="1010013100060001" shape="0" type="1" name="new balance" url="">
		<nd x="21.510681" y="86.056885" />
		<nd x="15.025879" y="86.056885" />
		<nd x="15.025879" y="94.919312" />
		<nd x="21.510681" y="94.919312" />
		<center x="18.2683105469" y="90.4880981445" />
	</feature>
	<feature id="1010013100060002" shape="0" type="1" name="adidas" url="">
		<nd x="28.905518" y="86.056885" />
		<nd x="23.821106" y="86.056885" />
		<nd x="21.510681" y="86.057129" />
		<nd x="21.510681" y="94.919312" />
		<nd x="28.905518" y="94.919312" />
		<center x="25.2081298828" y="90.4880981445" />
	</feature>
	<feature id="1010013100060003" shape="0" type="1" name="FILA" url="">
		<nd x="33.790283" y="86.056885" />
		<nd x="29.006104" y="86.056885" />
		<nd x="29.006104" y="94.919312" />
		<nd x="33.790283" y="94.919312" />
		<center x="31.3981933594" y="90.4880981445" />
	</feature>
	<feature id="1010013100060004" shape="0" type="1" name="ESPRIT" url="">
		<nd x="33.751526" y="86.056885" />
		<nd x="33.751526" y="94.919312" />
		<nd x="40.705688" y="94.919312" />
		<nd x="40.705688" y="86.057129" />
		<nd x="39.290527" y="86.056885" />
		<center x="37.2285766602" y="90.4880981445" />
	</feature>
	<feature id="1010013100060005" shape="0" type="1" name="馨亭" url="">
		<nd x="46.258301" y="86.057129" />
		<nd x="40.705688" y="86.057129" />
		<nd x="40.705688" y="94.919312" />
		<nd x="46.258301" y="94.919312" />
		<center x="43.4819946289" y="90.4882202148" />
	</feature>
	<feature id="1010013100060006" shape="0" type="1" name="MINE" url="">
		<nd x="51.899109" y="86.056885" />
		<nd x="48.280090" y="86.056885" />
		<nd x="46.258301" y="86.057129" />
		<nd x="46.258301" y="94.919312" />
		<nd x="51.899109" y="94.919312" />
		<center x="49.0786743164" y="90.4880981445" />
	</feature>
	<feature id="1010013100060007" shape="0" type="1" name="ZUCCHI" url="">
		<nd x="53.871521" y="86.055298" />
		<nd x="51.899109" y="86.057129" />
		<nd x="51.899109" y="94.919312" />
		<nd x="53.871521" y="94.919922" />
		<nd x="56.683472" y="94.919678" />
		<nd x="56.683472" y="86.055298" />
		<center x="54.2913818359" y="90.4876708984" />
	</feature>
	<feature id="1010013100060008" shape="0" type="1" name="SHERIPAN" url="">
		<nd x="58.984131" y="94.919922" />
		<nd x="64.091919" y="94.919922" />
		<nd x="64.091919" y="86.055298" />
		<nd x="56.683472" y="86.055298" />
		<nd x="56.683472" y="94.919312" />
		<center x="60.3876953125" y="90.4876098633" />
	</feature>
	<feature id="1010013100060009" shape="0" type="1" name="依娜" url="">
		<nd x="64.094116" y="94.919312" />
		<nd x="67.467896" y="94.919312" />
		<nd x="67.467896" y="86.056885" />
		<nd x="64.094116" y="86.056885" />
		<center x="65.7810058594" y="90.4880981445" />
	</feature>
	<feature id="1010013100060010" shape="0" type="1" name="罗莱家纺" url="">
		<nd x="67.467896" y="94.919312" />
		<nd x="70.992676" y="94.919312" />
		<nd x="70.992676" y="86.056885" />
		<nd x="67.467896" y="86.056885" />
		<center x="69.2302856445" y="90.4880981445" />
	</feature>
	<feature id="1010013100060011" shape="0" type="1" name="OSIM" url="">
		<nd x="70.941895" y="86.006104" />
		<nd x="70.941895" y="94.868530" />
		<nd x="76.284729" y="94.868530" />
		<nd x="76.284729" y="86.006287" />
		<nd x="74.315491" y="86.006104" />
		<center x="73.61328125" y="90.4373168945" />
	</feature>
	<feature id="1010013100060012" shape="0" type="1" name="YONEX" url="">
		<nd x="19.083313" y="77.597107" />
		<nd x="19.083313" y="82.966492" />
		<nd x="21.671082" y="82.966492" />
		<nd x="21.671082" y="77.597107" />
		<center x="20.3771972656" y="80.2817993164" />
	</feature>
	<feature id="1010013100060013" shape="0" type="1" name="Arena" url="">
		<nd x="21.671082" y="82.966309" />
		<nd x="25.568481" y="82.966309" />
		<nd x="25.568481" y="77.597107" />
		<nd x="21.671082" y="77.597107" />
		<center x="23.6198120117" y="80.2816772461" />
	</feature>
	<feature id="1010013100060014" shape="0" type="1" name="Puma" url="">
		<nd x="17.979919" y="77.597290" />
		<nd x="25.566711" y="77.597290" />
		<nd x="25.566711" y="72.024719" />
		<nd x="17.979919" y="72.024719" />
		<center x="21.7733154297" y="74.8109741211" />
	</feature>
	<feature id="1010013100060015" shape="0" type="1" name="热浪" url="">
		<nd x="28.052124" y="82.966492" />
		<nd x="29.277100" y="82.966492" />
		<nd x="29.277100" y="77.597290" />
		<nd x="25.566528" y="77.597290" />
		<nd x="25.566528" y="82.968323" />
		<center x="27.4216918945" y="80.2822265625" />
	</feature>
	<feature id="1010013100060016" shape="0" type="1" name="hosa" url="">
		<nd x="30.501099" y="82.968323" />
		<nd x="32.548889" y="82.968323" />
		<nd x="32.548889" y="77.597290" />
		<nd x="29.277100" y="77.597290" />
		<nd x="29.277100" y="82.966492" />
		<center x="30.9130859375" y="80.2825927734" />
	</feature>
	<feature id="1010013100060017" shape="0" type="1" name="Rapido" url="">
		<nd x="25.566528" y="77.597290" />
		<nd x="32.548889" y="77.597290" />
		<nd x="32.548889" y="72.024719" />
		<nd x="25.566528" y="72.024719" />
		<center x="29.0576782227" y="74.8109741211" />
	</feature>
	<feature id="1010013100060018" shape="0" type="1" name="泰普尔" url="">
		<nd x="34.747925" y="82.968323" />
		<nd x="39.699280" y="82.968323" />
		<nd x="39.699280" y="79.980713" />
		<nd x="34.747925" y="79.980713" />
		<center x="37.2235717773" y="81.4744873047" />
	</feature>
	<feature id="1010013100060019" shape="0" type="1" name="nshikawa 1566" url="">
		<nd x="39.699280" y="82.968323" />
		<nd x="44.130493" y="82.968323" />
		<nd x="44.130493" y="79.980713" />
		<nd x="39.699280" y="79.980713" />
		<center x="41.9149169922" y="81.4744873047" />
	</feature>
	<feature id="1010013100060020" shape="0" type="1" name="棉田" url="">
		<nd x="34.747925" y="79.980713" />
		<nd x="37.785706" y="79.980713" />
		<nd x="37.785706" y="76.959473" />
		<nd x="34.747925" y="76.959473" />
		<center x="36.266784668" y="78.4700927734" />
	</feature>
	<feature id="1010013100060021" shape="0" type="1" name="无印工坊" url="">
		<nd x="34.747925" y="76.959473" />
		<nd x="37.785706" y="76.959473" />
		<nd x="37.785706" y="74.307495" />
		<nd x="34.747925" y="74.307495" />
		<center x="36.266784668" y="75.6334838867" />
	</feature>
	<feature id="1010013100060022" shape="0" type="1" name="CARNIER THIEBAUT" url="">
		<nd x="34.747925" y="74.307495" />
		<nd x="44.130676" y="74.308289" />
		<nd x="44.130676" y="72.025696" />
		<nd x="34.747925" y="72.024902" />
		<center x="39.4392700195" y="73.1666259766" />
	</feature>
	<feature id="1010013100060023" shape="0" type="1" name="陶仨坊" url="">
		<nd x="46.111328" y="82.968323" />
		<nd x="49.743286" y="82.968323" />
		<nd x="49.743286" y="75.918884" />
		<nd x="46.111328" y="75.918884" />
		<center x="47.9273071289" y="79.4436035156" />
	</feature>
	<feature id="1010013100060024" shape="0" type="1" name="陆宝" url="">
		<nd x="49.743286" y="82.968323" />
		<nd x="53.268127" y="82.968323" />
		<nd x="53.268127" y="75.918884" />
		<nd x="49.743286" y="75.918884" />
		<center x="51.5056762695" y="79.4436035156" />
	</feature>
	<feature id="1010013100060025" shape="0" type="1" name="FRANZ" url="">
		<nd x="46.111328" y="75.918884" />
		<nd x="53.268127" y="75.918884" />
		<nd x="53.268127" y="72.159119" />
		<nd x="46.111328" y="72.159119" />
		<center x="49.6896972656" y="74.0390014648" />
	</feature>
	<feature id="1010013100060026" shape="0" type="1" name="象印" url="">
		<nd x="54.677917" y="82.968323" />
		<nd x="58.270081" y="82.968323" />
		<nd x="58.270081" y="77.597107" />
		<nd x="54.677917" y="77.597107" />
		<center x="56.4739990234" y="80.2827148438" />
	</feature>
	<feature id="1010013100060027" shape="0" type="1" name="Tiger" url="">
		<nd x="58.270081" y="82.968323" />
		<nd x="61.828308" y="82.968323" />
		<nd x="61.828308" y="77.597107" />
		<nd x="58.270081" y="77.597107" />
		<center x="60.0491943359" y="80.2827148438" />
	</feature>
	<feature id="1010013100060028" shape="0" type="1" name="Luminaec" url="">
		<nd x="54.677917" y="77.597290" />
		<nd x="58.270081" y="77.597290" />
		<nd x="58.270081" y="72.024719" />
		<nd x="54.677917" y="72.024719" />
		<center x="56.4739990234" y="74.8109741211" />
	</feature>
	<feature id="1010013100060029" shape="0" type="1" name="康宁餐具" url="">
		<nd x="58.270081" y="77.597290" />
		<nd x="61.828308" y="77.597290" />
		<nd x="61.828308" y="72.024719" />
		<nd x="58.270081" y="72.024719" />
		<center x="60.0491943359" y="74.8109741211" />
	</feature>
	<feature id="1010013100060030" shape="0" type="1" name="Dyson" url="">
		<nd x="63.389282" y="82.968323" />
		<nd x="67.770081" y="82.968323" />
		<nd x="67.770081" y="77.429321" />
		<nd x="63.389282" y="77.429321" />
		<center x="65.5797119141" y="80.1987915039" />
	</feature>
	<feature id="1010013100060031" shape="0" type="1" name="fmart" url="">
		<nd x="67.770081" y="82.968323" />
		<nd x="71.722900" y="82.968323" />
		<nd x="71.722900" y="77.429321" />
		<nd x="67.770081" y="77.429321" />
		<center x="69.7465209961" y="80.1987915039" />
	</feature>
	<feature id="1010013100060032" shape="0" type="1" name="BRITA" url="">
		<nd x="71.722900" y="82.968323" />
		<nd x="75.952515" y="82.968323" />
		<nd x="75.952515" y="77.429321" />
		<nd x="71.722900" y="77.429321" />
		<center x="73.8377075195" y="80.1987915039" />
	</feature>
	<feature id="1010013100060033" shape="0" type="1" name="飞利浦" url="">
		<nd x="63.389282" y="77.429504" />
		<nd x="66.737915" y="77.429504" />
		<nd x="66.737915" y="72.026123" />
		<nd x="63.389282" y="72.026123" />
		<center x="65.0635986328" y="74.7277832031" />
	</feature>
	<feature id="1010013100060034" shape="0" type="1" name="BRAUN" url="">
		<nd x="69.924927" y="72.025330" />
		<nd x="66.651917" y="72.025330" />
		<nd x="66.651917" y="77.429688" />
		<nd x="69.924927" y="77.429688" />
		<center x="68.2883911133" y="74.7274780273" />
	</feature>
	<feature id="1010013100060035" shape="0" type="1" name="Delonghi" url="">
		<nd x="73.258728" y="77.429504" />
		<nd x="75.952515" y="77.429504" />
		<nd x="75.952515" y="72.024902" />
		<nd x="73.258728" y="72.024902" />
		<center x="74.6055908203" y="74.7271728516" />
	</feature>
	<feature id="1010013100060036" shape="0" type="1" name="京钟" url="">
		<nd x="77.975281" y="81.625671" />
		<nd x="81.365723" y="81.625671" />
		<nd x="81.365723" y="79.477112" />
		<nd x="77.975281" y="79.477112" />
		<center x="79.6704711914" y="80.5513916016" />
	</feature>
	<feature id="1010013100060037" shape="0" type="1" name="BOSE" url="">
		<nd x="77.975281" y="79.477112" />
		<nd x="84.890686" y="79.477112" />
		<nd x="84.890686" y="72.142273" />
		<nd x="77.975281" y="72.142273" />
		<center x="81.4329833984" y="75.8096923828" />
	</feature>
	<feature id="1010013100060038" shape="0" type="1" name="sony" url="">
		<nd x="84.890686" y="79.477112" />
		<nd x="88.818115" y="79.477112" />
		<nd x="88.818115" y="72.142273" />
		<nd x="84.890686" y="72.142273" />
		<center x="86.8543701172" y="75.8096923828" />
	</feature>
	<feature id="1010013100060039" shape="0" type="1" name="adidas" url="">
		<nd x="15.025879" y="75.969116" />
		<nd x="15.025879" y="69.372925" />
		<nd x="22.092102" y="69.372925" />
		<nd x="22.092102" y="62.323120" />
		<nd x="2.000671" y="62.323120" />
		<nd x="2.000671" y="69.003479" />
		<nd x="5.055725" y="69.003479" />
		<nd x="5.055725" y="72.696472" />
		<nd x="8.110474" y="72.696472" />
		<nd x="8.110474" y="75.969116" />
		<center x="11.7015991211" y="67.6826782227" />
	</feature>
	<feature id="1010013100060040" shape="0" type="1" name="Nike" url="">
		<nd x="35.687683" y="51.597900" />
		<nd x="26.372070" y="51.597900" />
		<nd x="26.372070" y="62.071472" />
		<nd x="26.271484" y="62.323120" />
		<nd x="22.092102" y="62.323120" />
		<nd x="22.092102" y="69.372925" />
		<nd x="35.687683" y="69.372925" />
		<center x="29.9818725586" y="61.3120117188" />
	</feature>
	<feature id="1010013100060041" shape="0" type="1" name="VANS" url="">
		<nd x="35.687683" y="69.372925" />
		<nd x="40.320129" y="69.372925" />
		<nd x="40.320129" y="62.826721" />
		<nd x="35.687683" y="62.826721" />
		<center x="38.00390625" y="66.0997924805" />
	</feature>
	<feature id="1010013100060042" shape="0" type="1" name="Lacoste" url="">
		<nd x="35.687683" y="62.826721" />
		<nd x="40.320129" y="62.826721" />
		<nd x="40.320129" y="56.969116" />
		<nd x="35.687683" y="56.969116" />
		<center x="38.00390625" y="59.8978881836" />
	</feature>
	<feature id="1010013100060043" shape="0" type="1" name="Crocs" url="">
		<nd x="43.358521" y="51.597900" />
		<nd x="35.687683" y="51.597900" />
		<nd x="35.687683" y="56.969116" />
		<nd x="40.320129" y="56.969116" />
		<nd x="40.320129" y="55.626282" />
		<nd x="43.358521" y="55.626282" />
		<center x="39.2684936523" y="54.0620727539" />
	</feature>
	<feature id="1010013100060044" shape="0" type="1" name="Jeep" url="">
		<nd x="31.553284" y="51.543274" />
		<nd x="38.401306" y="51.543274" />
		<nd x="38.401306" y="47.685730" />
		<nd x="31.553284" y="47.685730" />
		<center x="34.9772949219" y="49.6145019531" />
	</feature>
	<feature id="1010013100060045" shape="0" type="1" name="贝纳通" url="">
		<nd x="38.401306" y="51.543274" />
		<nd x="44.779480" y="51.543274" />
		<nd x="44.779480" y="47.685730" />
		<nd x="38.401306" y="47.685730" />
		<center x="41.5903930664" y="49.6145019531" />
	</feature>
	<feature id="1010013100060046" shape="0" type="1" name="培乐多" url="">
		<nd x="52.930481" y="49.971924" />
		<nd x="56.759277" y="49.971924" />
		<nd x="56.759277" y="46.748108" />
		<nd x="52.930481" y="46.748108" />
		<center x="54.844909668" y="48.3599853516" />
	</feature>
	<feature id="1010013100060047" shape="0" type="1" name="Kuhn rikon" url="">
		<nd x="57.598511" y="69.372925" />
		<nd x="65.063477" y="69.372925" />
		<nd x="65.063477" y="65.445312" />
		<nd x="57.598511" y="65.445312" />
		<center x="61.3309936523" y="67.4091186523" />
	</feature>
	<feature id="1010013100060048" shape="0" type="1" name="三叉牌" url="">
		<nd x="57.598511" y="65.445312" />
		<nd x="61.330872" y="65.445312" />
		<nd x="61.330872" y="58.395691" />
		<nd x="57.598511" y="58.395691" />
		<center x="59.4647216797" y="61.9204711914" />
	</feature>
	<feature id="1010013100060049" shape="0" type="1" name="OQO" url="">
		<nd x="61.330872" y="65.445312" />
		<nd x="65.063477" y="65.445312" />
		<nd x="65.063477" y="58.395691" />
		<nd x="61.330872" y="58.395691" />
		<center x="63.1972045898" y="61.9204711914" />
	</feature>
	<feature id="1010013100060050" shape="0" type="1" name="WOLL" url="">
		<nd x="72.704895" y="62.323120" />
		<nd x="72.704895" y="59.536926" />
		<nd x="70.489319" y="59.536926" />
		<nd x="70.489319" y="56.079529" />
		<nd x="66.737915" y="56.079529" />
		<nd x="66.737915" y="62.323120" />
		<center x="69.2359008789" y="59.5618896484" />
	</feature>
	<feature id="1010013100060051" shape="0" type="1" name="WMF" url="">
		<nd x="63.389282" y="56.079529" />
		<nd x="70.489319" y="56.079529" />
		<nd x="70.489319" y="51.094482" />
		<nd x="63.389282" y="51.094482" />
		<center x="66.9392700195" y="53.5869750977" />
	</feature>
	<feature id="1010013100060052" shape="0" type="1" name="Fissler" url="">
		<nd x="56.239075" y="56.079529" />
		<nd x="63.389282" y="56.079529" />
		<nd x="63.389282" y="51.094482" />
		<nd x="56.239075" y="51.094482" />
		<center x="59.8142089844" y="53.5869750977" />
	</feature>
	<feature id="1010013100060053" shape="0" type="1" name="catimini" url="">
		<nd x="59.104492" y="51.002075" />
		<nd x="67.715088" y="51.002075" />
		<nd x="67.715088" y="45.614319" />
		<nd x="59.104492" y="45.614319" />
		<center x="63.4097900391" y="48.3082275391" />
	</feature>
	<feature id="1010013100060054" shape="0" type="1" name="KP" url="">
		<nd x="59.159485" y="41.127075" />
		<nd x="67.770081" y="41.127075" />
		<nd x="67.770081" y="35.940491" />
		<nd x="59.159485" y="35.940491" />
		<center x="63.4647827148" y="38.5338134766" />
	</feature>
	<feature id="1010013100060055" shape="0" type="1" name="ELAND KIDS" url="">
		<nd x="59.159485" y="35.940491" />
		<nd x="67.770081" y="35.940491" />
		<nd x="67.770081" y="30.451904" />
		<nd x="59.159485" y="30.451904" />
		<center x="63.4647827148" y="33.1962280273" />
	</feature>
	<feature id="1010013100060056" shape="0" type="1" name="Paw in Paw" url="">
		<nd x="59.159485" y="30.451904" />
		<nd x="67.770081" y="30.451904" />
		<nd x="67.770081" y="24.862671" />
		<nd x="59.159485" y="24.862671" />
		<center x="63.4647827148" y="27.6572875977" />
	</feature>
	<feature id="1010013100060057" shape="0" type="1" name="保险柜专卖" url="">
		<nd x="59.159729" y="24.862671" />
		<nd x="67.770081" y="24.862671" />
		<nd x="67.770081" y="23.707886" />
		<nd x="59.158325" y="23.707092" />
		<center x="63.4641113281" y="24.2850952148" />
	</feature>
	<feature id="1010013100060058" shape="0" type="1" name="味千拉面" url="">
		<nd x="76.330322" y="46.179321" />
		<nd x="81.164307" y="46.179321" />
		<nd x="81.164307" y="34.379700" />
		<nd x="67.770081" y="34.379700" />
		<nd x="67.770081" y="51.094482" />
		<nd x="76.330322" y="51.094482" />
		<center x="73.958984375" y="42.0366210938" />
	</feature>
	<feature id="1010013100060059" shape="0" type="1" name="红双喜" url="">
		<nd x="19.083313" y="77.597107" />
		<nd x="17.981873" y="77.597107" />
		<nd x="17.981873" y="82.966492" />
		<nd x="19.083313" y="82.966492" />
		<center x="18.5325927734" y="80.2817993164" />
	</feature>
	<feature id="1010013100060060" shape="0" type="1" name="UCHINO" url="">
		<nd x="44.130676" y="74.308289" />
		<nd x="37.785889" y="74.307495" />
		<nd x="37.785889" y="79.980896" />
		<nd x="44.130676" y="79.980896" />
		<center x="40.958190918" y="77.1444091797" />
	</feature>
	<feature id="1010013100060061" shape="0" type="1" name="双立人" url="">
		<nd x="66.737915" y="69.372925" />
		<nd x="75.738281" y="69.372925" />
		<nd x="75.738281" y="62.323486" />
		<nd x="66.737915" y="62.323486" />
		<center x="71.2380981445" y="65.8482055664" />
	</feature>
	<feature id="1010013100060062" shape="0" type="1" name="FOPPAPEORETTI" url="">
		<nd x="75.738281" y="62.323730" />
		<nd x="75.738281" y="69.372925" />
		<nd x="78.344727" y="69.372925" />
		<nd x="78.344727" y="62.323730" />
		<center x="77.0415039062" y="65.8483276367" />
	</feature>
	<feature id="1010013100060063" shape="0" type="1" name="SONY" url="">
		<nd x="85.597473" y="69.371521" />
		<nd x="89.573914" y="69.370483" />
		<nd x="89.572327" y="63.634521" />
		<nd x="85.595886" y="63.635498" />
		<center x="87.5848999023" y="66.5029907227" />
	</feature>
	<feature id="1010013100060064" shape="0" type="1" name="kenwood" url="">
		<nd x="69.924927" y="72.025330" />
		<nd x="69.924927" y="77.429688" />
		<nd x="73.172729" y="77.429688" />
		<nd x="73.172729" y="72.025330" />
		<center x="71.548828125" y="74.7274780273" />
	</feature>
	<feature id="1010013100060065" shape="0" type="1" name="利快" url="">
		<nd x="76.284729" y="94.868530" />
		<nd x="85.932678" y="94.775696" />
		<nd x="85.796875" y="86.661072" />
		<nd x="81.365723" y="86.661072" />
		<nd x="81.365723" y="86.060913" />
		<nd x="76.335510" y="86.057129" />
		<center x="80.9943237305" y="90.5903930664" />
	</feature>
	<feature id="1010013100060066" shape="0" type="1" name="金利来" url="">
		<nd x="39.701111" y="16.411682" />
		<nd x="39.693909" y="21.042480" />
		<nd x="47.456482" y="21.042480" />
		<nd x="47.456482" y="16.411682" />
		<center x="43.5770263672" y="18.7274780273" />
	</feature>
	<feature id="1010013100060067" shape="0" type="1" name="been kids" url="">
		<nd x="59.104492" y="45.614319" />
		<nd x="67.770081" y="45.614319" />
		<nd x="67.770081" y="41.127075" />
		<nd x="59.104492" y="41.127075" />
		<center x="63.4373168945" y="43.3707275391" />
	</feature>
	<feature id="1010013100060068" shape="0" type="1" name="鄂尔多斯" url="">
		<nd x="47.456482" y="7.018127" />
		<nd x="47.456482" y="5.224670" />
		<nd x="38.088501" y="5.222473" />
		<nd x="38.088501" y="13.031921" />
		<nd x="31.155884" y="13.029480" />
		<nd x="31.155884" y="16.411499" />
		<nd x="39.701111" y="16.411499" />
		<nd x="39.701111" y="7.018127" />
		<center x="35.2310791016" y="14.7213134766" />
	</feature>
	<feature id="1010013100060069" shape="0" type="1" name="呷哺呷哺" url="">
		<nd x="76.531677" y="21.690491" />
		<nd x="74.467102" y="24.862671" />
		<nd x="67.770081" y="24.862671" />
		<nd x="67.770081" y="34.379700" />
		<nd x="81.164307" y="34.379700" />
		<nd x="81.164307" y="21.690491" />
		<center x="74.9407958984" y="28.8491821289" />
	</feature>
	<feature id="1010013100060070" shape="0" type="1" name="Disney Princess" url="">
		<nd x="61.962524" y="21.263916" />
		<nd x="64.916687" y="21.263916" />
		<nd x="64.916687" y="18.014526" />
		<nd x="61.962524" y="18.014526" />
		<center x="63.4395751953" y="19.6392211914" />
	</feature>
	<feature id="1010013100060071" shape="0" type="1" name="mickey mouse" url="">
		<nd x="65.781128" y="21.263916" />
		<nd x="67.770081" y="21.263916" />
		<nd x="67.770081" y="18.014526" />
		<nd x="65.781128" y="18.014526" />
		<center x="66.7755737305" y="19.6392211914" />
	</feature>
	<feature id="1010013100060072" shape="0" type="1" name="NIKE KIDS" url="">
		<nd x="20.430481" y="46.917908" />
		<nd x="29.661926" y="46.917908" />
		<nd x="29.661926" y="41.781494" />
		<nd x="20.430481" y="41.781494" />
		<center x="25.0462036133" y="44.3496704102" />
	</feature>
	<feature id="1010013100060073" shape="0" type="1" name="adidas kids" url="">
		<nd x="20.430481" y="41.781494" />
		<nd x="29.661926" y="41.781494" />
		<nd x="29.661926" y="36.276489" />
		<nd x="20.430481" y="36.276489" />
		<center x="25.0462036133" y="39.0289916992" />
	</feature>
	<feature id="1010013100060074" shape="0" type="1" name="JNBY by JNBY" url="">
		<nd x="20.430481" y="36.276489" />
		<nd x="29.661926" y="36.276489" />
		<nd x="29.661926" y="30.737488" />
		<nd x="20.430481" y="30.737488" />
		<center x="25.0462036133" y="33.507019043" />
	</feature>
	<feature id="1010013100060075" shape="0" type="1" name="好孩子" url="">
		<nd x="20.430481" y="30.737488" />
		<nd x="29.665100" y="30.737488" />
		<nd x="29.665100" y="25.366089" />
		<nd x="20.430481" y="25.366089" />
		<center x="25.0477905273" y="28.0518188477" />
	</feature>
	<feature id="1010013100060076" shape="0" type="1" name="海辰贝贝" url="">
		<nd x="32.011902" y="43.820923" />
		<nd x="36.838318" y="43.820923" />
		<nd x="36.838318" y="39.029114" />
		<nd x="32.011902" y="39.029114" />
		<center x="34.4251098633" y="41.424987793" />
	</feature>
	<feature id="1010013100060077" shape="0" type="1" name="法纳贝儿" url="">
		<nd x="36.838318" y="43.820923" />
		<nd x="40.828308" y="43.820923" />
		<nd x="40.828308" y="39.029114" />
		<nd x="36.838318" y="39.029114" />
		<center x="38.8333129883" y="41.424987793" />
	</feature>
	<feature id="1010013100060078" shape="0" type="1" name="小猪班纳" url="">
		<nd x="32.011902" y="39.029114" />
		<nd x="36.838318" y="39.029114" />
		<nd x="36.838318" y="34.303894" />
		<nd x="32.011902" y="34.303894" />
		<center x="34.4251098633" y="36.6665039062" />
	</feature>
	<feature id="1010013100060079" shape="0" type="1" name="水孩儿" url="">
		<nd x="36.838318" y="39.029114" />
		<nd x="40.828308" y="39.029114" />
		<nd x="40.828308" y="34.303894" />
		<nd x="36.838318" y="34.303894" />
		<center x="38.8333129883" y="36.6665039062" />
	</feature>
	<feature id="1010013100060080" shape="0" type="1" name="AIMER KIDS" url="">
		<nd x="43.257874" y="43.820923" />
		<nd x="47.321899" y="43.820923" />
		<nd x="47.321899" y="40.774292" />
		<nd x="43.257874" y="40.774292" />
		<center x="45.2899169922" y="42.2976074219" />
	</feature>
	<feature id="1010013100060081" shape="0" type="1" name="callise" url="">
		<nd x="43.257874" y="40.774292" />
		<nd x="47.321899" y="40.774292" />
		<nd x="47.321899" y="37.921082" />
		<nd x="43.257874" y="37.921082" />
		<center x="45.2899169922" y="39.3477172852" />
	</feature>
	<feature id="1010013100060082" shape="0" type="1" name="丽婴房" url="">
		<nd x="32.011902" y="33.196289" />
		<nd x="37.013489" y="33.196289" />
		<nd x="37.013489" y="28.420898" />
		<nd x="32.011902" y="28.420898" />
		<center x="34.5126953125" y="30.80859375" />
	</feature>
	<feature id="1010013100060083" shape="0" type="1" name="Hallmark" url="">
		<nd x="37.013489" y="33.196289" />
		<nd x="40.828308" y="33.196289" />
		<nd x="40.828308" y="28.420898" />
		<nd x="37.013489" y="28.420898" />
		<center x="38.9208984375" y="30.80859375" />
	</feature>
	<feature id="1010013100060084" shape="0" type="1" name="Senbodulun" url="">
		<nd x="32.011902" y="28.420898" />
		<nd x="37.013489" y="28.420898" />
		<nd x="37.013489" y="23.704529" />
		<nd x="32.011902" y="23.704529" />
		<center x="34.5126953125" y="26.0626831055" />
	</feature>
	<feature id="1010013100060085" shape="0" type="1" name="英氏" url="">
		<nd x="37.032715" y="28.420898" />
		<nd x="40.828308" y="28.420898" />
		<nd x="40.828308" y="23.704529" />
		<nd x="37.032715" y="23.704529" />
		<center x="38.930480957" y="26.0626831055" />
	</feature>
	<feature id="1010013100060086" shape="0" type="1" name="chicco" url="">
		<nd x="43.459106" y="30.065918" />
		<nd x="47.590881" y="30.065918" />
		<nd x="47.590881" y="23.704529" />
		<nd x="43.459106" y="23.704529" />
		<center x="45.5250244141" y="26.8851928711" />
	</feature>
	<feature id="1010013100060087" shape="0" type="1" name="芭比" url="">
		<nd x="49.712280" y="43.820923" />
		<nd x="53.236328" y="43.820923" />
		<nd x="53.236328" y="40.774292" />
		<nd x="49.712280" y="40.774292" />
		<center x="51.4743041992" y="42.2976074219" />
	</feature>
	<feature id="1010013100060088" shape="0" type="1" name="LEGO" url="">
		<nd x="53.236328" y="43.820923" />
		<nd x="56.759277" y="43.820923" />
		<nd x="56.759277" y="40.774292" />
		<nd x="53.236328" y="40.774292" />
		<center x="54.9978027344" y="42.2976074219" />
	</feature>
	<feature id="1010013100060089" shape="0" type="1" name="恒盛天怡" url="">
		<nd x="49.712280" y="40.774292" />
		<nd x="56.759277" y="40.774292" />
		<nd x="56.759277" y="35.009094" />
		<nd x="49.712280" y="35.009094" />
		<center x="53.2357788086" y="37.8917236328" />
	</feature>
	<feature id="1010013100060090" shape="0" type="1" name="canlemon" url="">
		<nd x="49.712280" y="31.207275" />
		<nd x="53.236328" y="31.207275" />
		<nd x="53.236328" y="27.514709" />
		<nd x="49.712280" y="27.514709" />
		<center x="51.4743041992" y="29.3610229492" />
	</feature>
	<feature id="1010013100060091" shape="0" type="1" name="惠葆" url="">
		<nd x="49.712280" y="27.514709" />
		<nd x="53.236084" y="27.514709" />
		<nd x="53.236084" y="23.704529" />
		<nd x="49.712280" y="23.704529" />
		<center x="51.4741821289" y="25.6096191406" />
	</feature>
	<feature id="1010013100060092" shape="0" type="1" name="兄妹猫" url="">
		<nd x="53.236328" y="31.207275" />
		<nd x="56.759277" y="31.207275" />
		<nd x="56.759277" y="28.689697" />
		<nd x="53.236328" y="28.689697" />
		<center x="54.9978027344" y="29.9484863281" />
	</feature>
	<feature id="1010013100060093" shape="0" type="1" name="MOONSTAR" url="">
		<nd x="53.236328" y="28.689697" />
		<nd x="56.759277" y="28.689697" />
		<nd x="56.759277" y="26.306274" />
		<nd x="53.236328" y="26.306274" />
		<center x="54.9978027344" y="27.4979858398" />
	</feature>
	<feature id="1010013100060094" shape="0" type="1" name="NATURINA" url="">
		<nd x="53.236328" y="26.306274" />
		<nd x="56.759277" y="26.306274" />
		<nd x="56.759277" y="23.704529" />
		<nd x="53.236328" y="23.704529" />
		<center x="54.9978027344" y="25.0053710938" />
	</feature>
	<feature id="1010013100060095" shape="0" type="1" name="米皇" url="">
		<nd x="27.177917" y="21.041870" />
		<nd x="31.155701" y="21.041870" />
		<nd x="31.155701" y="13.029297" />
		<nd x="27.177917" y="13.029297" />
		<center x="29.166809082" y="17.0355834961" />
	</feature>
	<feature id="1010013100060096" shape="0" type="1" name="珍贝" url="">
		<nd x="50.951904" y="5.224487" />
		<nd x="47.456482" y="5.224487" />
		<nd x="47.456482" y="21.041870" />
		<nd x="52.798279" y="21.041870" />
		<nd x="52.798279" y="13.482483" />
		<nd x="50.951904" y="13.482483" />
		<center x="49.7426147461" y="13.9655151367" />
	</feature>
	<feature id="1010013100060097" shape="0" type="1" name="帕罗" url="">
		<nd x="52.798279" y="21.041870" />
		<nd x="59.713318" y="21.041870" />
		<nd x="59.713318" y="16.772278" />
		<nd x="52.798279" y="16.772278" />
		<center x="56.2557983398" y="18.9071044922" />
	</feature>
	<feature id="1010013100060098" shape="0" type="1" name="三星手机" url="">
		<nd x="78.344482" y="62.323486" />
		<nd x="78.344482" y="69.372925" />
		<nd x="83.833130" y="69.372925" />
		<nd x="85.597473" y="69.371521" />
		<nd x="85.595520" y="62.323120" />
		<nd x="83.833130" y="62.323486" />
		<center x="81.9703979492" y="65.8483276367" />
	</feature>
	<feature id="1010013100060099" shape="0" type="1" name="方太" url="">
		<nd x="85.595520" y="55.642883" />
		<nd x="88.784729" y="55.642883" />
		<nd x="88.784729" y="52.084473" />
		<nd x="85.595520" y="52.084473" />
		<center x="87.1901245117" y="53.8637084961" />
	</feature>
	<feature id="1010013100060100" shape="0" type="1" name="SAMSUNG" url="">
		<nd x="91.906311" y="74.441711" />
		<nd x="98.418884" y="74.441711" />
		<nd x="98.418884" y="71.588318" />
		<nd x="91.906311" y="71.588318" />
		<center x="95.1625976562" y="73.0150146484" />
	</feature>
	<feature id="1010013100060101" shape="0" type="1" name="SHARP" url="">
		<nd x="91.906311" y="71.588501" />
		<nd x="98.418884" y="71.588501" />
		<nd x="98.418884" y="69.372925" />
		<nd x="91.906311" y="69.372925" />
		<center x="95.1625976562" y="70.4807128906" />
	</feature>
	<feature id="1010013100060102" shape="0" type="1" name="SIEMENS" url="">
		<nd x="91.906311" y="69.372925" />
		<nd x="98.418884" y="69.372925" />
		<nd x="98.418884" y="66.318115" />
		<nd x="91.906311" y="66.318115" />
		<center x="95.1625976562" y="67.8455200195" />
	</feature>
	<feature id="1010013100060103" shape="0" type="1" name="SIEMENS" url="">
		<nd x="91.906311" y="66.318115" />
		<nd x="98.418884" y="66.318115" />
		<nd x="98.418884" y="58.395691" />
		<nd x="91.906311" y="58.395691" />
		<center x="95.1625976562" y="62.3568725586" />
	</feature>
	<feature id="1010013100060104" shape="0" type="1" name="ARISTON" url="">
		<nd x="91.906311" y="58.395508" />
		<nd x="98.418884" y="58.395508" />
		<nd x="98.418884" y="51.278931" />
		<nd x="91.906311" y="51.278931" />
		<center x="95.1625976562" y="54.8372192383" />
	</feature>
	<feature id="1010013100060105" shape="0" type="1" name="见现冰激凌" url="">
		<nd x="84.588318" y="44.970703" />
		<nd x="90.530090" y="51.279114" />
		<nd x="96.270508" y="51.279114" />
		<nd x="96.270508" y="44.970703" />
		<center x="91.7459716797" y="47.7662963867" />
	</feature>
	<feature id="1010013100060106" shape="0" type="1" name="权味" url="">
		<nd x="84.588318" y="44.970703" />
		<nd x="96.270508" y="44.970703" />
		<nd x="96.270508" y="32.617310" />
		<nd x="84.017700" y="32.617310" />
		<nd x="84.017700" y="44.366516" />
		<center x="90.1508789062" y="38.7871704102" />
	</feature>
	<feature id="1010013100060107" shape="0" type="1" name="姑姑宴" url="">
		<nd x="84.017700" y="32.617310" />
		<nd x="96.270508" y="32.617310" />
		<nd x="96.270508" y="20.683289" />
		<nd x="84.017700" y="20.683289" />
		<center x="90.1441040039" y="26.6503295898" />
	</feature>
	<feature id="1010013100060108" shape="0" type="1" name="和合谷" url="">
		<nd x="82.423279" y="18.014526" />
		<nd x="84.017700" y="20.683289" />
		<nd x="96.270508" y="20.683289" />
		<nd x="96.270508" y="5.224487" />
		<nd x="80.912476" y="5.224487" />
		<nd x="80.912476" y="18.014526" />
		<center x="88.7640991211" y="12.7794799805" />
	</feature>
	<feature id="1010013100060109" shape="0" type="1" name="儿童套房" url="">
		<nd x="48.189697" y="33.997498" />
		<nd x="48.189697" y="32.593079" />
		<nd x="46.996094" y="31.454895" />
		<nd x="44.053894" y="31.454895" />
		<nd x="42.862305" y="32.593079" />
		<nd x="42.862305" y="35.401917" />
		<nd x="44.053894" y="36.540283" />
		<nd x="46.996094" y="36.540283" />
		<nd x="48.189697" y="35.401917" />
		<center x="45.5258178711" y="33.9976196289" />
	</feature>
	<feature id="1010013100060110" shape="0" type="1" name="BABYROOM" url="">
		<nd x="20.431885" y="25.367676" />
		<nd x="27.175903" y="25.367676" />
		<nd x="27.175903" y="21.041870" />
		<nd x="20.451111" y="21.041870" />
		<nd x="20.441711" y="23.429321" />
		<center x="23.8090209961" y="23.2058105469" />
	</feature>
	<feature id="1010013100060111" shape="0" type="1" name="爱康" url="">
		<nd x="48.050476" y="67.660095" />
		<nd x="51.156921" y="67.660095" />
		<nd x="51.156921" y="62.119080" />
		<nd x="48.050476" y="62.119080" />
		<center x="49.6036987305" y="64.8895874023" />
	</feature>
	<feature id="1010013100060112" shape="0" type="1" name="converse" url="">
		<nd x="43.358521" y="55.626282" />
		<nd x="47.119324" y="55.626282" />
		<nd x="47.119324" y="51.597900" />
		<nd x="43.358521" y="51.597900" />
		<center x="45.2388916016" y="53.612121582" />
	</feature>
	<feature id="1010013100060113" shape="0" type="1" name="三菱" url="">
		<nd x="85.595886" y="63.635498" />
		<nd x="89.574890" y="63.634521" />
		<nd x="89.573486" y="58.043091" />
		<nd x="85.594727" y="58.044128" />
		<center x="87.584777832" y="60.8392944336" />
	</feature>
	<feature id="1010013100060114" shape="0" type="1" name="雪莲" url="">
		<nd x="47.456482" y="16.411499" />
		<nd x="47.456482" y="7.018127" />
		<nd x="39.701111" y="7.018127" />
		<nd x="39.701111" y="16.411682" />
		<center x="43.5787963867" y="11.7149047852" />
	</feature>
	<feature id="1010013100060115" shape="0" type="1" name="兔皇" url="">
		<nd x="34.961487" y="16.411682" />
		<nd x="31.156311" y="16.411682" />
		<nd x="31.156311" y="21.042480" />
		<nd x="34.961487" y="21.042480" />
		<center x="33.0588989258" y="18.7271118164" />
	</feature>
	<feature id="1010013100060116" shape="0" type="1" name="蕾沃尔" url="">
		<nd x="39.701111" y="16.411682" />
		<nd x="34.961731" y="16.411682" />
		<nd x="34.961731" y="21.042480" />
		<nd x="39.693909" y="21.042480" />
		<center x="37.3295898438" y="18.7265014648" />
	</feature>
	<feature id="1010013100060117" shape="0" type="2" name="" url="">
		<nd x="8.110474" y="72.696472" />
		<nd x="5.055725" y="72.696472" />
		<nd x="5.055725" y="69.003479" />
		<nd x="2.000671" y="69.003479" />
		<nd x="2.000671" y="84.378479" />
		<nd x="8.110474" y="84.378479" />
		<center x="4.84710693359" y="77.4882202148" />
	</feature>
	<feature id="1010013100060118" shape="0" type="2" name="" url="">
		<nd x="8.110474" y="54.157104" />
		<nd x="15.394897" y="54.157104" />
		<nd x="15.394897" y="8.161926" />
		<nd x="2.000671" y="8.161926" />
		<nd x="2.000671" y="62.079712" />
		<nd x="8.110474" y="62.079712" />
		<center x="8.43249511719" y="33.1234130859" />
	</feature>
	<feature id="1010013100060119" shape="0" type="2" name="" url="">
		<nd x="11.567871" y="54.367310" />
		<nd x="11.567871" y="62.323120" />
		<nd x="26.271484" y="62.323120" />
		<nd x="26.372070" y="62.071472" />
		<nd x="26.372070" y="51.614685" />
		<nd x="29.662109" y="51.614685" />
		<nd x="29.662109" y="46.917908" />
		<nd x="20.430481" y="46.917908" />
		<nd x="20.430481" y="54.367310" />
		<center x="16.0914916992" y="58.3452758789" />
	</feature>
	<feature id="1010013100060120" shape="0" type="2" name="" url="">
		<nd x="81.365723" y="86.661072" />
		<nd x="85.796875" y="86.661072" />
		<nd x="85.796875" y="89.682312" />
		<nd x="98.418884" y="89.682312" />
		<nd x="98.418884" y="74.441711" />
		<nd x="91.906311" y="74.441711" />
		<nd x="91.906311" y="79.477112" />
		<nd x="81.365723" y="79.477112" />
		<center x="89.8922729492" y="84.5797119141" />
	</feature>
	<feature id="1010013100060121" shape="0" type="2" name="" url="">
		<nd x="72.704895" y="59.536926" />
		<nd x="72.704895" y="62.323120" />
		<nd x="85.595520" y="62.323120" />
		<nd x="85.595520" y="52.151489" />
		<nd x="81.164307" y="46.179321" />
		<nd x="76.330322" y="46.179321" />
		<nd x="76.330322" y="51.077271" />
		<nd x="70.489319" y="51.077271" />
		<nd x="70.489319" y="59.536926" />
		<center x="78.51171875" y="55.2728881836" />
	</feature>
	<feature id="1010013100060122" shape="0" type="2" name="" url="">
		<nd x="67.770081" y="21.252319" />
		<nd x="71.102478" y="21.252319" />
		<nd x="71.102478" y="19.407898" />
		<nd x="67.770081" y="19.407898" />
		<center x="69.4362792969" y="20.330078125" />
	</feature>
	<feature id="1010013100060123" shape="0" type="2" name="" url="">
		<nd x="61.962524" y="18.014526" />
		<nd x="67.770081" y="18.014526" />
		<nd x="67.770081" y="5.224487" />
		<nd x="50.951904" y="5.224487" />
		<nd x="50.951904" y="13.482483" />
		<nd x="61.962524" y="13.482483" />
		<center x="59.3610229492" y="9.353515625" />
	</feature>
	<feature id="1010013100060124" shape="0" type="2" name="" url="">
		<nd x="71.118530" y="18.014526" />
		<nd x="80.912476" y="18.014526" />
		<nd x="80.912476" y="5.224487" />
		<nd x="71.118530" y="5.224487" />
		<center x="76.0155029297" y="11.6195068359" />
	</feature>
	<feature id="1010013100060125" shape="0" type="2" name="" url="">
		<nd x="20.451111" y="21.041870" />
		<nd x="27.175903" y="21.041870" />
		<nd x="27.175903" y="13.031677" />
		<nd x="38.088501" y="13.031677" />
		<nd x="38.088501" y="5.222473" />
		<nd x="20.502686" y="5.222473" />
		<nd x="20.474487" y="15.130676" />
		<center x="29.2697753906" y="9.12707519531" />
	</feature>
	<feature id="1010013100060126" shape="0" type="0" name="" url="">
		<nd x="85.932678" y="89.538696" />
		<nd x="98.554688" y="89.538696" />
		<nd x="98.554688" y="51.135498" />
		<nd x="96.406311" y="51.135498" />
		<nd x="96.406311" y="5.080872" />
		<nd x="19.861328" y="5.080872" />
		<nd x="19.861328" y="8.035095" />
		<nd x="2.136475" y="8.035095" />
		<nd x="2.136475" y="94.775696" />
		<nd x="85.932678" y="94.775696" />
		<center x="49.7083129883" y="50.1226806641" />
	</feature>
	<feature id="1010013100060127" shape="0" type="3" name="" url="">
		<nd x="51.287476" y="69.372925" />
		<nd x="55.248474" y="69.372925" />
		<nd x="55.248474" y="59.830872" />
		<nd x="51.287476" y="59.830872" />
		<center x="53.2680053711" y="64.6019287109" />
	</feature>
	<feature id="1010013100060128" shape="0" type="3" name="" url="">
		<nd x="47.321899" y="59.830872" />
		<nd x="43.358521" y="59.830872" />
		<nd x="43.358521" y="69.372925" />
		<nd x="47.321899" y="69.372925" />
		<center x="45.3402099609" y="64.6019287109" />
	</feature>
	<feature id="1010013100060129" shape="2" type="2" name="Escalator" url="Escalator.png">
		<nd x="53.252075" y="64.643921" />
		<center x="53.2520751953" y="64.6439208984" />
	</feature>
	<feature id="1010013100060130" shape="2" type="2" name="Escalator" url="Escalator.png">
		<nd x="45.148071" y="64.518677" />
		<center x="45.1480712891" y="64.5186767578" />
	</feature>
	<feature id="1010013100060131" shape="2" type="2" name="Stairs" url="Stairs.png">
		<nd x="5.074890" y="82.160278" />
		<center x="5.07489013672" y="82.1602783203" />
	</feature>
	<feature id="1010013100060132" shape="2" type="2" name="Stairs" url="Stairs.png">
		<nd x="5.338684" y="74.776489" />
		<center x="5.33868408203" y="74.7764892578" />
	</feature>
	<feature id="1010013100060133" shape="2" type="2" name="Stairs" url="Stairs.png">
		<nd x="24.061890" y="56.580688" />
		<center x="24.0618896484" y="56.5806884766" />
	</feature>
	<feature id="1010013100060134" shape="2" type="2" name="Stairs" url="Stairs.png">
		<nd x="23.666321" y="49.196716" />
		<center x="23.6663208008" y="49.1967163086" />
	</feature>
	<feature id="1010013100060135" shape="2" type="2" name="Stairs" url="Stairs.png">
		<nd x="83.000671" y="58.426514" />
		<center x="83.0006713867" y="58.4265136719" />
	</feature>
	<feature id="1010013100060136" shape="2" type="2" name="Stairs" url="Stairs.png">
		<nd x="76.539917" y="53.679688" />
		<center x="76.5399169922" y="53.6796875" />
	</feature>
	<feature id="1010013100060137" shape="2" type="2" name="Toilet" url="Toilet.png">
		<nd x="5.338684" y="58.822083" />
		<center x="5.33868408203" y="58.8220825195" />
	</feature>
	<feature id="1010013100060138" shape="2" type="2" name="Toilet" url="Toilet.png">
		<nd x="79.572510" y="48.801086" />
		<center x="79.5725097656" y="48.8010864258" />
	</feature>
	<feature id="1010013100060139" shape="2" type="2" name="Stairs" url="Stairs.png">
		<nd x="88.670471" y="82.687683" />
		<center x="88.6704711914" y="82.6876831055" />
	</feature>
	<feature id="1010013100060140" shape="2" type="2" name="Elevator" url="Elevator.png">
		<nd x="96.054321" y="76.886108" />
		<center x="96.0543212891" y="76.8861083984" />
	</feature>
	<feature id="1010013100060141" shape="2" type="2" name="Stairs" url="Stairs.png">
		<nd x="75.748718" y="12.673096" />
		<center x="75.7487182617" y="12.6730957031" />
	</feature>
	<feature id="1010013100060142" shape="2" type="2" name="Stairs" url="Stairs.png">
		<nd x="64.672913" y="10.827271" />
		<center x="64.6729125977" y="10.8272705078" />
	</feature>
	<feature id="1010013100060143" shape="2" type="2" name="Stairs" url="Stairs.png">
		<nd x="69.609314" y="20.098083" />
		<center x="69.6093139648" y="20.0980834961" />
	</feature>
	<feature id="1010013100060144" shape="2" type="2" name="Stairs" url="Stairs.png">
		<nd x="24.647095" y="10.604675" />
		<center x="24.6470947266" y="10.604675293" />
	</feature>
	<feature id="1010013100060145" shape="2" type="2" name="Stairs" url="Stairs.png">
		<nd x="50.358521" y="53.589111" />
		<center x="50.3585205078" y="53.5891113281" />
	</feature>
</floor>
